odoo/addons/product_cost_price_avco_sync_mrp/README.rst
odoo/addons/product_cost_price_avco_sync_mrp/__init__.py
odoo/addons/product_cost_price_avco_sync_mrp/__manifest__.py
odoo/addons/product_cost_price_avco_sync_mrp/i18n/es.po
odoo/addons/product_cost_price_avco_sync_mrp/i18n/product_cost_price_avco_sync_mrp.pot
odoo/addons/product_cost_price_avco_sync_mrp/models/__init__.py
odoo/addons/product_cost_price_avco_sync_mrp/models/stock_valuation_layer.py
odoo/addons/product_cost_price_avco_sync_mrp/readme/CONTRIBUTORS.rst
odoo/addons/product_cost_price_avco_sync_mrp/readme/DESCRIPTION.rst
odoo/addons/product_cost_price_avco_sync_mrp/static/description/icon.png
odoo/addons/product_cost_price_avco_sync_mrp/static/description/index.html
odoo/addons/product_cost_price_avco_sync_mrp/tests/__init__.py
odoo/addons/product_cost_price_avco_sync_mrp/tests/test_product_cost_price_avco_sync_mrp.py
odoo13_addon_product_cost_price_avco_sync_mrp-13.0.1.0.1.dist-info/METADATA
odoo13_addon_product_cost_price_avco_sync_mrp-13.0.1.0.1.dist-info/WHEEL
odoo13_addon_product_cost_price_avco_sync_mrp-13.0.1.0.1.dist-info/top_level.txt
odoo13_addon_product_cost_price_avco_sync_mrp-13.0.1.0.1.dist-info/RECORD
