Metadata-Version: 2.1
Name: odoo13-addon-product-cost-price-avco-sync-mrp
Version: 13.0.1.0.1
Summary: Set product cost price from updated moves that implies productions
Home-page: https://github.com/OCA/stock-logistics-workflow
Author: Tecnativa, Odoo Community Association (OCA)
Author-email: support@odoo-community.org
License: AGPL-3
Platform: UNKNOWN
Classifier: Programming Language :: Python
Classifier: Framework :: Odoo
Classifier: Framework :: Odoo :: 13.0
Classifier: License :: OSI Approved :: GNU Affero General Public License v3
Classifier: Development Status :: 5 - Production/Stable
Requires-Python: >=3.5
Requires-Dist: odoo13-addon-product-cost-price-avco-sync
Requires-Dist: odoo <13.1dev,>=13.0a
